bigquery_duckdb_toolkit/__init__.py
bigquery_duckdb_toolkit/bigquery_client.py
bigquery_duckdb_toolkit/bigquery_to_pandas.py
bigquery_duckdb_toolkit/interaction_service.py
bigquery_duckdb_toolkit-1.0.3.dist-info/LICENSE
bigquery_duckdb_toolkit-1.0.3.dist-info/METADATA
bigquery_duckdb_toolkit-1.0.3.dist-info/WHEEL
bigquery_duckdb_toolkit-1.0.3.dist-info/top_level.txt
bigquery_duckdb_toolkit-1.0.3.dist-info/RECORD
