Metadata-Version: 2.1
Name: bigquery_duckdb_toolkit
Version: 1.0.3
Summary: Toolkit para consultas e manipulação de dados no BigQuery com integração com DuckDB.
Home-page: https://github.com/ResultadosDigitais/bigquery_duckdb_toolkit
Author: Tiago Navarro
Author-email: tiagornavarro@gmail.com
Classifier: Programming Language :: Python :: 3
Classifier: License :: OSI Approved :: MIT License
Classifier: Operating System :: OS Independent
Classifier: Intended Audience :: Developers
Classifier: Intended Audience :: Science/Research
Classifier: Topic :: Software Development :: Libraries
Classifier: Topic :: Scientific/Engineering :: Information Analysis
Requires-Python: >=3.8
License-File: LICENSE
Requires-Dist: db-dtypes
Requires-Dist: ipython
Requires-Dist: google-auth
Requires-Dist: google-cloud-bigquery
Requires-Dist: pandas
Requires-Dist: tabulate
Requires-Dist: duckdb
Requires-Dist: jinja2
